[
    {
        "Title" : "Pre-Survey",
        "Link" : "pre.php",
        "Due" : "09/29/17",
        "Active" : 1
    },
    {
        "Title" : "HW 1",
        "Link" : "hw1.php",
        "Due" : "10/04/17",
        "Active" : 1
    },
    {
        "Title" : "HW 2",
        "Link" : "hw2.php",
        "Due" : "10/20/17",
        "Active" : 1
    },
    {
        "Title" : "Mid-Survey",
        "Link" : "mid.php",
        "Due" : "11/02/17",
        "Active" : 1
    },
    {
        "Title" : "HW3",
        "Link" : "hw3.php",
        "Due" : "11/03/17",
        "Active" : 1
    },
    {
        "Title" : "HW4",
        "Link" : "hw4.php",
        "Due" : "11/17/17",
        "Active" : 1
    },
    {
        "Title" : "HW5",
        "Link" : "hw5.php",
        "Due" : "12/01/17",
        "Active" : 1
    }
]
